mechanizecache/__init__.py
mechanizecache-0.0.3.dist-info/DESCRIPTION.rst
mechanizecache-0.0.3.dist-info/METADATA
mechanizecache-0.0.3.dist-info/RECORD
mechanizecache-0.0.3.dist-info/WHEEL
mechanizecache-0.0.3.dist-info/metadata.json
mechanizecache-0.0.3.dist-info/top_level.txt
