Metadata-Version: 2.0
Name: mechanizecache
Version: 0.0.3
Summary: Improve mechanize to handle cookies
Home-page: https://pypi.python.org/pypi/mechanizecache
Author: Lionel Young
Author-email: lionelyoung@gmail.com
License: MIT
Keywords: mechanize web scrape tools
Platform: UNKNOWN
Classifier: Development Status :: 3 - Alpha
Classifier: Intended Audience :: Developers
Classifier: License :: OSI Approved :: MIT License
Classifier: Programming Language :: Python :: 2.7
Requires-Dist: lxml
Requires-Dist: mechanize
